uprintgen/__init__.py
uprintgen/command_line.py
uprintgen/microprint_generator.py
uprintgen/svg_microprint_generator.py
uPrintGen-1.2.1.dist-info/LICENSE
uPrintGen-1.2.1.dist-info/METADATA
uPrintGen-1.2.1.dist-info/WHEEL
uPrintGen-1.2.1.dist-info/entry_points.txt
uPrintGen-1.2.1.dist-info/top_level.txt
uPrintGen-1.2.1.dist-info/RECORD
