Metadata-Version: 2.1
Name: uPrintGen
Version: 1.2.1
Summary: Microprint generator
Author-email: AlphaSteam <sebastian.alfaro@outlook.cl>
License: GNU GENERAL PUBLIC LICENSE
Project-URL: Homepage, https://github.com/AlphaSteam/uPrintGen
Keywords: microprint,generator,software_visualization,software,visualization
Classifier: Programming Language :: Python
Classifier: Programming Language :: Python :: 3
Classifier: License :: OSI Approved :: GNU General Public License v3 (GPLv3)
Requires-Python: >=3.0
License-File: LICENSE
Requires-Dist: svgwrite
Requires-Dist: tqdm
